Workbook

Sheet Read me
A1: Lumen Rollout · Project control workbook
A2: Oracle EPM rollout (EPBCS and FCCS) at Maison Lumen · status at 25 September 2026
A4: Purpose | B4: One place for the registers the project manager reviews every week and presents to the steering committee.
A5: Owner | B5: Gaurav Sharma, project manager
A6: Status date | B6: 46290
A8: Sheet | B8: Content
A9: Dashboard | B9: Calculated summary: risks, issues, change control, UAT exit criteria and the go/no-go decision
A10: Risks | B10: Risk register: probability × impact, level, owner, response, status
A11: Assumptions | B11: What the plan takes for granted, with the date by which it must be checked
A12: Issues | B12: Risks that have happened, with an owner and an action
A13: Dependencies | B13: Work outside the project team; status calculated from the dates
A14: Decisions | B14: Decisions of the steering committee and of the project manager
A15: Change log | B15: Change requests, their impact, who decides, and the contingency released
A16: UAT test plan | B16: User acceptance test cases, traced to the requirements of the design documents
A17: Defects | B17: Defects raised in testing, by severity
A18: Go-no-go | B18: Cutover checklist for the EPBCS go-live
A20: Legend | B20: Yellow cells are inputs: edit them. Grey cells are formulas: do not overwrite them.
... A25: Note | B25: Portfolio sample. Maison Lumen, its people and all figures are fictional.

Sheet Dashboard
A1: Dashboard · status at 25 September 2026
A2: Every value on this sheet is calculated from the registers.
A3: RAID
A4: Open risks | B4: =COUNTIF(Risks!K2:K9,"Open")
A5: Open high risks (score 15 or more) | B5: =COUNTIFS(Risks!F2:F9,">=15",Risks!K2:K9,"Open") | C5: Go-live condition
A6: Open risks blocking go-live (score 20 or more) | B6: =COUNTIFS(Risks!F2:F9,">=20",Risks!K2:K9,"Open") | C6: Go-live blocker
A7: Open issues | B7: =COUNTIF(Issues!F2:F4,"Open")
A8: Late dependencies | B8: =COUNTIF(Dependencies!F2:F5,"Late")
A9: Change control
A10: Change requests awaiting decision | B10: =COUNTIF('Change log'!I2:I6,"Submitted")
A11: Contingency left (k€) | B11: ='Change log'!C11
A12: Authorised budget (k€) | B12: ='Change log'!C12 | C12: Work budget + contingency released
A13: UAT
A14: Test cases in scope | B14: =COUNTIF('UAT test plan'!F2:F25,"<>Descoped")
A15: Passed | B15: =COUNTIF('UAT test plan'!F2:F25,"Passed")
A16: Failed | B16: =COUNTIF('UAT test plan'!F2:F25,"Failed")
A17: Blocked | B17: =COUNTIF('UAT test plan'!F2:F25,"Blocked")
A18: Not run | B18: =COUNTIF('UAT test plan'!F2:F25,"Not run")
A19: Executed | B19: =(B15+B16)/B14 | C19: Passed + failed, over cases in scope
A20: Pass rate | B20: =B15/B14
A21: Open critical defects | B21: =COUNTIFS(Defects!C2:C7,"Critical",Defects!F2:F7,"<>Closed")
A22: Open major defects | B22: =COUNTIFS(Defects!C2:C7,"Major",Defects!F2:F7,"<>Closed")
A23: Security tests passed | B23: =COUNTIFS('UAT test plan'!B2:B25,"Security",'UAT test plan'!F2:F25,"Passed")/COUNTIF('UAT test plan'!B2:B25,"Security")
A24: Exit criteria
A25: C1 · 100 % of cases executed | B25: =IF(B19>=1,"Met","Blocker")
A26: C2 · At least 95 % passed (90 % with conditions) | B26: =IF(B20>=0.95,"Met",IF(B20>=0.9,"Condition","Blocker"))
A27: C3 · No critical defect open | B27: =IF(B21=0,"Met","Blocker")
A28: C4 · No major defect (2 at most with a workaround) | B28: =IF(B22=0,"Met",IF(B22<=2,"Condition","Blocker"))
A29: C5 · 100 % of security tests passed | B29: =IF(B23>=1,"Met","Blocker")
A30: Go/no-go
A31: Critical checklist actions not done | B31: =COUNTIFS('Go-no-go'!D2:D17,"Yes",'Go-no-go'!F2:F17,"No") | C31: Blockers
A32: Other checklist actions not done | B32: =COUNTIFS('Go-no-go'!D2:D17,"No",'Go-no-go'!F2:F17,"No") | C32: Conditions
A33: Blocking points | B33: =COUNTIF(B25:B29,"Blocker")+B31+B6 | C33: Exit criteria + critical actions + risks of 20 or more
A34: Conditions | B34: =COUNTIF(B25:B29,"Condition")+B32+B5-B6 | C34: Exit criteria + other actions + high risks below 20
A35: Calculated decision | B35: =IF(B33>0,"NO GO",IF(B34>0,"GO WITH CONDITIONS","GO")) | C35: Recorded by the go/no-go committee

Sheet Risks
A1: ID | B1: Risk | C1: Owner | D1: P (1-5) | E1: I (1-5) | F1: Score | G1: Level | H1: Blocks go-live | I1: Response | J1: Action | K1: Status
A2: R1 | B2: Poor quality of historical ERP data | C2: IT / ERP | D2: 4 | E2: 4 | F2: =D2*E2 | G2: =IF(F2>=15,"High",IF(F2>=8,"Medium","Low")) | H2: =IF(F2>=20,"Yes","No") | I2: Reduce | J2: Data cleansing and monthly reconciliation with accounting | K2: Open
A3: R2 | B3: Key users unavailable during testing (budget season) | C3: Sponsor (CFO) | D3: 4 | E3: 3 | F3: =D3*E3 | G3: =IF(F3>=15,"High",IF(F3>=8,"Medium","Low")) | H3: =IF(F3>=20,"Yes","No") | I3: Reduce | J3: Test schedule approved by the CFO, half-days blocked | K3: Open
A4: R3 | B4: Delay in the ERP data flows (Data Management) | C4: IT / ERP | D4: 3 | E4: 4 | F4: =D4*E4 | G4: =IF(F4>=15,"High",IF(F4>=8,"Medium","Low")) | H4: =IF(F4>=20,"Yes","No") | I4: Fallback | J4: Manual file loads until the flows are ready | K4: Open
A5: R4 | B5: Complex consolidation rules (NCI, FX) | C5: Consolidation team | D5: 2 | E5: 4 | F5: =D5*E5 | G5: =IF(F5>=15,"High",IF(F5>=8,"Medium","Low")) | H5: =IF(F5>=20,"Yes","No") | I5: Reduce | J5: Dedicated test cases, auditor review | K5: Open
A6: R5 | B6: Resistance to change (attachment to Excel) | C6: Project manager | D6: 3 | E6: 3 | F6: =D6*E6 | G6: =IF(F6>=15,"High",IF(F6>=8,"Medium","Low")) | H6: =IF(F6>=20,"Yes","No") | I6: Reduce | J6: Champions in each entity, demos, hands-on training | K6: Open
A7: R6 | B7: Dependence on one key consultant | C7: Project manager | D7: 2 | E7: 3 | F7: =D7*E7 | G7: =IF(F7>=15,"High",IF(F7>=8,"Medium","Low")) | H7: =IF(F7>=20,"Yes","No") | I7: Reduce | J7: Documentation and pairing with the internal team | K7: Open
A8: R7 | B8: Oracle's October update during testing (test 2 Oct, production 16 Oct) | C8: IT / ERP | D8: 3 | E8: 2 | F8: =D8*E8 | G8: =IF(F8>=15,"High",IF(F8>=8,"Medium","Low")) | H8: =IF(F8>=20,"Yes","No") | I8: Accept | J8: Regression tests after each update, before production | K8: Open
A9: R8 | B9: Project budget overrun | C9: Project manager | D9: 3 | E9: 3 | F9: =D9*E9 | G9: =IF(F9>=15,"High",IF(F9>=8,"Medium","Low")) | H9: =IF(F9>=20,"Yes","No") | I9: Reduce | J9: Monthly earned value, scope trade-offs with the sponsor | K9: Open

Sheet Assumptions
A1: ID | B1: Assumption | C1: Owner | D1: Check by | E1: Status | F1: Note
A2: AS1 | B2: Key users give two half-days a week to testing | C2: Sponsor (CFO) | D2: 46279 | E2: Confirmed
A3: AS2 | B3: The group chart of accounts stays frozen until the FCCS go-live | C3: Consolidation team | D3: 46157 | E3: Confirmed
A4: AS3 | B4: Oracle EPM licences cover 60 users at no extra cost | C4: IT / ERP | D4: 46108 | E4: Confirmed
A5: AS4 | B5: The 2024–2025 history can be extracted from the ERP without rework | C5: IT / ERP | D5: 46203 | E5: False | F5: Proved false: became issue I1

Sheet Issues
A1: ID | B1: Issue | C1: Priority | D1: Owner | E1: Action | F1: Status
A2: I1 | B2: ERP flows about a month late: 2024–2025 history not yet loaded | C2: High | D2: IT / ERP | E2: Manual loads for testing; escalated to the committee | F2: Open
A3: I2 | B3: Since Oracle's 4 September update, journals are unavailable in the test environment | C3: Medium | D3: IT / ERP | E3: Support request (SR) opened with Oracle | F3: Open
A4: I3 | B4: Two key users absent the week of 5 October | C4: Medium | D4: Sponsor (CFO) | E4: Stand-ins named by the CFO | F4: Open

Sheet Dependencies
A1: ID | B1: Dependency | C1: Owner | D1: Needed by | E1: Forecast | F1: Status
A2: DP1 | B2: ERP flows delivered by the ERP team before performance testing | C2: IT / ERP | D2: 46290 | E2: 46290 | F2: =IF(E2<D2,"On track",IF(E2=D2,"Just in time","Late"))
A3: DP2 | B3: Test environment available after each Oracle update | C3: IT / ERP | D3: 46300 | E3: 46297 | F3: =IF(E3<D3,"On track",IF(E3=D3,"Just in time","Late"))
A4: DP3 | B4: Closing exchange rates supplied by treasury before the parallel run | C4: Consolidation team | D4: 46356 | E4: 46353 | F4: =IF(E4<D4,"On track",IF(E4=D4,"Just in time","Late"))
A5: DP4 | B5: FY27 budget calendar approved by executive management | C5: Sponsor (CFO) | D5: 46295 | E5: 46304 | F5: =IF(E5<D5,"On track",IF(E5=D5,"Just in time","Late"))

Sheet Decisions
A1: Date | B1: Forum | C1: Decision
A2: 46108 | B2: COPIL | C2: Project charter approved: 480 k€ budget plus 48 k€ contingency; tolerances of ±10 working days on go-lives and +5 % on cost
A3: 46157 | B3: COPIL | C3: Design document signed off; CR-01 approved (FCCS go-live on the year-end close)
A4: 46206 | B4: COPIL | C4: CR-05 rejected: workforce planning moved to phase 2
A5: 46262 | B5: COPIL | C5: Build complete accepted; testing stage authorised
A6: 46273 | B6: Project manager | C6: CR-02 approved within the project manager's delegation (8 k€ of contingency)

Sheet Change log
A1: ID | B1: Request | C1: Type | D1: Requested by | E1: Date | F1: Cost (k€) | G1: Time (working days) | H1: Change authority | I1: Status | J1: Contingency released (k€) | K1: Note
A2: CR-01 | B2: Align the FCCS go-live on the year-end close (January) rather than December | C2: Time | D2: Consolidation team | E2: 46157 | F2: 0 | G2: 20 | H2: =IF(OR(C2="Scope",F2>10,G2>0),"COPIL","Project manager") | I2: Approved | J2: =IF(AND(I2="Approved",C2="Cost"),F2,0) | K2: Baseline updated at design sign-off
A3: CR-02 | B3: Manual file loads for testing until the ERP flows are ready | C3: Cost | D3: IT / ERP | E3: 46273 | F3: 8 | G3: 0 | H3: =IF(OR(C3="Scope",F3>10,G3>0),"COPIL","Project manager") | I3: Approved | J3: =IF(AND(I3="Approved",C3="Cost"),F3,0) | K3: Within the project manager's delegation
A4: CR-03 | B4: Release 30 k€ of contingency: ERP delay and extended testing | C4: Cost | D4: Project manager | E4: 46287 | F4: 30 | G4: 0 | H4: =IF(OR(C4="Scope",F4>10,G4>0),"COPIL","Project manager") | I4: Submitted | J4: =IF(AND(I4="Approved",C4="Cost"),F4,0) | K4: Awaiting the steering committee
A5: CR-04 | B5: Defer the CFO dashboard (case U22) to phase 2 | C5: Scope | D5: FP&A key users | E5: 46289 | F5: 0 | G5: 0 | H5: =IF(OR(C5="Scope",F5>10,G5>0),"COPIL","Project manager") | I5: Submitted | J5: =IF(AND(I5="Approved",C5="Cost"),F5,0) | K5: Reduces test scope; no go-live impact
A6: CR-05 | B6: Add driver-based workforce planning to phase 1 | C6: Scope | D6: FP&A key users | E6: 46206 | F6: 40 | G6: 30 | H6: =IF(OR(C6="Scope",F6>10,G6>0),"COPIL","Project manager") | I6: Rejected | J6: =IF(AND(I6="Approved",C6="Cost"),F6,0) | K6: Incompatible with the budget calendar; phase 2
B8: Work budget (k€) | C8: 480
B9: Contingency approved at charter (k€) | C9: 48
B10: Contingency released (k€) | C10: =SUM(J2:J6)
B11: Contingency left (k€) | C11: =C9-C10
B12: Authorised budget (k€) | C12: =C8+C10

Sheet UAT test plan
A1: ID | B1: Area | C1: Test case | D1: Requirement | E1: Tester | F1: Status | G1: Open defect
A2: U01 | B2: Planning | C2: Driver-based budget entry | D2: REQ-02 | E2: FP&A key users | F2: Passed
A3: U02 | B3: Planning | C3: Revenue = units × price | D3: REQ-02 | E3: FP&A key users | F3: Passed
A4: U03 | B4: Planning | C4: Payroll and 13th month | D4: REQ-03 | E4: FP&A key users | F4: Failed | G4: D1
A5: U04 | B5: Planning | C5: Head-office cost allocation | D5: REQ-04 | E5: FP&A key users | F5: Passed
A6: U05 | B6: Planning | C6: Top-down spreading | D6: REQ-05 | E6: FP&A key users | F6: Passed
A7: U06 | B7: Planning | C7: Budget approval workflow | D7: REQ-06 | E7: FP&A key users | F7: Passed
A8: U07 | B8: Planning | C8: What-if simulation | D8: REQ-07 | E8: FP&A key users | F8: Not run
A9: U08 | B9: Planning | C9: Rolling 9+3 forecast | D9: REQ-01 | E9: FP&A key users | F9: Not run
A10: U09 | B10: Consolidation | C10: IAS 21 translation | D10: FCCS design | E10: Consolidation team | F10: Passed
A11: U10 | B11: Consolidation | C11: Intercompany matching | D11: FCCS design | E11: Consolidation team | F11: Failed | G11: D2
A12: U11 | B12: Consolidation | C12: Automatic eliminations | D12: FCCS design | E12: Consolidation team | F12: Passed
A13: U12 | B13: Consolidation | C13: Goodwill and NCI | D13: FCCS design | E13: Consolidation team | F13: Passed
A14: U13 | B14: Consolidation | C14: Journals and approval | D14: FCCS design | E14: Consolidation team | F14: Blocked | G14: D5
A15: U14 | B15: Consolidation | C15: Consolidated statements | D15: FCCS design | E15: Consolidation team | F15: Not run
A16: U15 | B16: Consolidation | C16: Close checks | D16: FCCS design | E16: Consolidation team | F16: Not run
A17: U16 | B17: Data | C17: Monthly ERP actuals load | D17: REQ-08 | E17: IT / ERP | F17: Passed
A18: U17 | B18: Data | C18: Mapping table and kick-outs | D18: REQ-08 | E18: IT / ERP | F18: Passed
A19: U18 | B19: Data | C19: Exchange rate load | D19: FCCS design | E19: IT / ERP | F19: Not run
A20: U19 | B20: Data | C20: 2024–2025 history reconciled | D20: REQ-08 | E20: IT / ERP | F20: Blocked | G20: D6
A21: U20 | B21: Reports | C21: Budget variance report | D21: REQ-09 | E21: FP&A key users | F21: Passed
A22: U21 | B22: Reports | C22: Consolidation pack | D22: FCCS design | E22: FP&A key users | F22: Not run
A23: U22 | B23: Reports | C23: CFO dashboard | D23: REQ-12 | E23: FP&A key users | F23: Not run
A24: U23 | B24: Security | C24: Access restricted by entity | D24: REQ-10 | E24: IT / ERP | F24: Failed | G24: D4
A25: U24 | B25: Security | C25: Approver profiles | D25: REQ-10 | E25: IT / ERP | F25: Not run

Sheet Defects
A1: ID | B1: Test case | C1: Severity | D1: Description | E1: Owner | F1: Status
A2: D1 | B2: U03 | C2: Critical | D2: The 13th month is not calculated in December for Paris | E2: EPM consultant | F2: Open
A3: D2 | B3: U10 | C3: Major | D3: FX differences are flagged 'to investigate' instead of 'FX difference' | E3: EPM consultant | F3: Open
A4: D3 | B4: U20 | C4: Minor | D4: Truncated label in the variance report | E4: EPM consultant | F4: Closed
A5: D4 | B5: U23 | C5: Critical | D5: A Lille controller can see Paris data | E5: EPM consultant | F5: Open
A6: D5 | B6: U13 | C6: Major | D6: Journals unavailable since Oracle's 4 September update (test environment) | E6: IT / ERP | F6: Open
A7: D6 | B7: U19 | C7: Major | D7: 2024 history incomplete: ERP flow not delivered | E7: IT / ERP | F7: Open

Sheet Go-no-go
A1: ID | B1: Area | C1: Action | D1: Critical | E1: Owner | F1: Done
A2: K1 | B2: Data | C2: 2024–2025 history loaded and reconciled | D2: Yes | E2: IT / ERP | F2: No
A3: K2 | B3: Data | C3: Exchange rates and opening balances approved | D3: Yes | E3: Consolidation team | F3: Yes
A4: K3 | B4: Data | C4: ERP mapping tables frozen | D4: Yes | E4: IT / ERP | F4: Yes
A5: K4 | B5: Technical | C5: ERP flows scheduled in production | D5: Yes | E5: IT / ERP | F5: No
A6: K5 | B6: Technical | C6: Application snapshot taken before cutover | D6: Yes | E6: EPM consultant | F6: No
A7: K6 | B7: Technical | C7: Production access rights checked by entity | D7: Yes | E7: EPM consultant | F7: No
A8: K15 | B8: Technical | C8: Mock cutover (dress rehearsal) completed, timings measured | D8: Yes | E8: IT / ERP | F8: No
A9: K16 | B9: Technical | C9: Regression tests passed after Oracle's October update | D9: Yes | E9: FP&A key users | F9: No
A10: K7 | B10: Users | C10: At least 90 % of users trained | D10: Yes | E10: Project manager | F10: No
A11: K8 | B11: Users | C11: User guides published | D11: No | E11: EPM consultant | F11: Yes
A12: K9 | B12: Users | C12: Champions named in each entity | D12: No | E12: Sponsor (CFO) | F12: Yes
... A17: K14 | B17: Governance | C17: Launch communication sent | D17: No | E17: Project manager | F17: No
